pinventory/__init__.py
pinventory/__main__.py
pinventory/inventory.py
pinventory/network.py
pinventory/transform/__init__.py
pinventory/transform/hostsvars.py
pinventory/transform/inventory.py
pinventory-0.5.0.dist-info/DESCRIPTION.rst
pinventory-0.5.0.dist-info/METADATA
pinventory-0.5.0.dist-info/RECORD
pinventory-0.5.0.dist-info/WHEEL
pinventory-0.5.0.dist-info/entry_points.txt
pinventory-0.5.0.dist-info/metadata.json
pinventory-0.5.0.dist-info/top_level.txt
