Metadata-Version: 2.0
Name: pinventory
Version: 0.5.0
Summary: An Ansible dynamic inventory for locating and categorising Raspberry Pis on the LAN.
Home-page: https://github.com/sixty-north/pinventory
Author: Sixty North AS
Author-email: rob@sixty-north.com
License: MIT
Platform: UNKNOWN
Classifier: Development Status :: 4 - Beta
Classifier: Intended Audience :: Developers
Classifier: License :: Other/Proprietary License
Classifier: Programming Language :: Python :: 3.6
Requires-Dist: docopt
